infocenka/__init__.py
infocenka/db_functions/__init__.py
infocenka/db_functions/functions.py
infocenka/geo/__init__.py
infocenka/geo/functions.py
infocenka/metrics/__init__.py
infocenka/metrics/functions.py
infocenka/orionn_preprocessing/__init__.py
infocenka/orionn_preprocessing/functions.py
infocenka/preprocessing/__init__.py
infocenka/preprocessing/functions.py
infocenka-0.0.1.dist-info/LICENSE
infocenka-0.0.1.dist-info/METADATA
infocenka-0.0.1.dist-info/WHEEL
infocenka-0.0.1.dist-info/top_level.txt
infocenka-0.0.1.dist-info/RECORD
